<?xml version="1.0" encoding="utf-8"?>
<DynamicProperties>
  <DynamicPropertiesCategory Category="3D Component" Type="File">
    <DynamicProperty>Title</DynamicProperty>
    <DynamicProperty>Description</DynamicProperty>
    <DynamicProperty>Part Number</DynamicProperty>
    <DynamicProperty>Material</DynamicProperty>
    <DynamicProperty>Dimensions/Size</DynamicProperty>
    <DynamicProperty>Mass</DynamicProperty>
    <DynamicProperty>Length (Cut)</DynamicProperty>
    <DynamicProperty>Source File</DynamicProperty>
    <DynamicProperty>Spare-Wear Part</DynamicProperty>
    <DynamicProperty>Semi finished</DynamicProperty>
    <DynamicProperty>Stock Number</DynamicProperty>
    <DynamicProperty Hidden="True">Application Version</DynamicProperty>
  </DynamicPropertiesCategory>
  <DynamicPropertiesCategory Category="Part" Type="File">
    <DynamicProperty>Title</DynamicProperty>
    <DynamicProperty>Material</DynamicProperty>
    <DynamicProperty>Part Number</DynamicProperty>
    <DynamicProperty>Weight</DynamicProperty>
    <DynamicProperty>Spare-Wear Part</DynamicProperty>
    <DynamicProperty>Dimensions/Size</DynamicProperty>
    <DynamicProperty>Description 2</DynamicProperty>
    <DynamicProperty>Description</DynamicProperty>
    <DynamicProperty>Stock Number</DynamicProperty>
    <DynamicProperty>Length (Cut)</DynamicProperty>
    <DynamicProperty>Semi finished</DynamicProperty>
    <DynamicProperty>Ident Number</DynamicProperty>
    <DynamicProperty>Project Number</DynamicProperty>
    <DynamicProperty>Source File</DynamicProperty>
    <DynamicProperty>Author</DynamicProperty>
    <DynamicProperty>Project</DynamicProperty>
    <DynamicProperty>Mfg Approved By</DynamicProperty>
    <DynamicProperty>Manager</DynamicProperty>
    <DynamicProperty>Engr Approved By</DynamicProperty>
    <DynamicProperty>FDS Key</DynamicProperty>
    <DynamicProperty>Designer</DynamicProperty>
    <DynamicProperty>Engineer</DynamicProperty>
    <DynamicProperty>Comments</DynamicProperty>
    <DynamicProperty>Cost</DynamicProperty>
    <DynamicProperty>Keywords</DynamicProperty>
    <DynamicProperty>Subject</DynamicProperty>
    <DynamicProperty>Company</DynamicProperty>
    <DynamicProperty>Project Type</DynamicProperty>
    <DynamicProperty>Checked By</DynamicProperty>
    <DynamicProperty>Application Version</DynamicProperty>
    <DynamicProperty>Mass</DynamicProperty>
    <DynamicProperty>Sub-Type</DynamicProperty>
  </DynamicPropertiesCategory>
  <DynamicPropertiesCategory Category="Assembly" Type="File">
    <DynamicProperty>Title</DynamicProperty>
    <DynamicProperty>Material</DynamicProperty>
    <DynamicProperty>Part Number</DynamicProperty>
    <DynamicProperty>Weight</DynamicProperty>
    <DynamicProperty>Spare-Wear Part</DynamicProperty>
    <DynamicProperty>Dimensions/Size</DynamicProperty>
    <DynamicProperty>Description 2</DynamicProperty>
    <DynamicProperty>Description</DynamicProperty>
    <DynamicProperty>Stock Number</DynamicProperty>
    <DynamicProperty>Length (Cut)</DynamicProperty>
    <DynamicProperty>Semi finished</DynamicProperty>
    <DynamicProperty>Ident Number</DynamicProperty>
    <DynamicProperty>Project Number</DynamicProperty>
    <DynamicProperty>Source File</DynamicProperty>
    <DynamicProperty>Author</DynamicProperty>
    <DynamicProperty>Project</DynamicProperty>
    <DynamicProperty>Mfg Approved By</DynamicProperty>
    <DynamicProperty>Manager</DynamicProperty>
    <DynamicProperty>Engr Approved By</DynamicProperty>
    <DynamicProperty>FDS Key</DynamicProperty>
    <DynamicProperty>Designer</DynamicProperty>
    <DynamicProperty>Engineer</DynamicProperty>
    <DynamicProperty>Comments</DynamicProperty>
    <DynamicProperty>Cost</DynamicProperty>
    <DynamicProperty>Keywords</DynamicProperty>
    <DynamicProperty>Subject</DynamicProperty>
    <DynamicProperty>Company</DynamicProperty>
    <DynamicProperty>Project Type</DynamicProperty>
    <DynamicProperty>Checked By</DynamicProperty>
  </DynamicPropertiesCategory>
  <DynamicPropertiesCategory Category="Sheet Metal Part" Type="File">
    <DynamicProperty>Title</DynamicProperty>
    <DynamicProperty>Material</DynamicProperty>
    <DynamicProperty>Part Number</DynamicProperty>
    <DynamicProperty>Weight</DynamicProperty>
    <DynamicProperty>Spare-Wear Part</DynamicProperty>
    <DynamicProperty>Dimensions/Size</DynamicProperty>
    <DynamicProperty>Description 2</DynamicProperty>
    <DynamicProperty>Description</DynamicProperty>
    <DynamicProperty>Stock Number</DynamicProperty>
    <DynamicProperty>Length (Cut)</DynamicProperty>
    <DynamicProperty>Semi finished</DynamicProperty>
    <DynamicProperty>Ident Number</DynamicProperty>
    <DynamicProperty>Project Number</DynamicProperty>
    <DynamicProperty>Source File</DynamicProperty>
    <DynamicProperty>Author</DynamicProperty>
    <DynamicProperty>Project</DynamicProperty>
    <DynamicProperty>Mfg Approved By</DynamicProperty>
    <DynamicProperty>Manager</DynamicProperty>
    <DynamicProperty>Engr Approved By</DynamicProperty>
    <DynamicProperty>FDS Key</DynamicProperty>
    <DynamicProperty>Designer</DynamicProperty>
    <DynamicProperty>Engineer</DynamicProperty>
    <DynamicProperty>Comments</DynamicProperty>
    <DynamicProperty>Cost</DynamicProperty>
    <DynamicProperty>Keywords</DynamicProperty>
    <DynamicProperty>Subject</DynamicProperty>
    <DynamicProperty>Company</DynamicProperty>
    <DynamicProperty>Project Type</DynamicProperty>
    <DynamicProperty>Checked By</DynamicProperty>
  </DynamicPropertiesCategory>
  <DynamicPropertiesCategory Category="Office" Type="File">
    <DynamicProperty>Title</DynamicProperty>
    <DynamicProperty>Author</DynamicProperty>
    <DynamicProperty Hidden="True">Comments</DynamicProperty>
    <DynamicProperty>Engr Approved By</DynamicProperty>
    <DynamicProperty>Keywords</DynamicProperty>
    <DynamicProperty>Subject</DynamicProperty>
  </DynamicPropertiesCategory>
  <DynamicPropertiesCategory Category="Base" Type="File">
    <DynamicProperty>Author</DynamicProperty>
    <DynamicProperty>Manager</DynamicProperty>
    <DynamicProperty>Engr Approved By</DynamicProperty>
    <DynamicProperty>Engineer</DynamicProperty>
    <DynamicProperty>Designer</DynamicProperty>
    <DynamicProperty>Stock Number</DynamicProperty>
    <DynamicProperty>Part Number</DynamicProperty>
    <DynamicProperty>Mfg Approved By</DynamicProperty>
    <DynamicProperty>Material</DynamicProperty>
    <DynamicProperty>Cost</DynamicProperty>
    <DynamicProperty>Company</DynamicProperty>
    <DynamicProperty>Title</DynamicProperty>
    <DynamicProperty>Subject</DynamicProperty>
    <DynamicProperty>Keywords</DynamicProperty>
    <DynamicProperty>Comments</DynamicProperty>
    <DynamicProperty>Description</DynamicProperty>
    <DynamicProperty>Project</DynamicProperty>
  </DynamicPropertiesCategory>
  <DynamicPropertiesCategory Category="Engineering" Type="File">
    <DynamicProperty>Author</DynamicProperty>
    <DynamicProperty>Manager</DynamicProperty>
    <DynamicProperty>Engr Approved By</DynamicProperty>
    <DynamicProperty>Engineer</DynamicProperty>
    <DynamicProperty>Designer</DynamicProperty>
    <DynamicProperty>Stock Number</DynamicProperty>
    <DynamicProperty>Part Number</DynamicProperty>
    <DynamicProperty>Material</DynamicProperty>
    <DynamicProperty>Description</DynamicProperty>
    <DynamicProperty>Cost</DynamicProperty>
    <DynamicProperty>Checked By</DynamicProperty>
    <DynamicProperty>Company</DynamicProperty>
    <DynamicProperty>Title</DynamicProperty>
    <DynamicProperty>Subject</DynamicProperty>
    <DynamicProperty>Keywords</DynamicProperty>
    <DynamicProperty>Comments</DynamicProperty>
    <DynamicProperty>Mfg Approved By</DynamicProperty>
    <DynamicProperty>Project</DynamicProperty>
  </DynamicPropertiesCategory>
  <DynamicPropertiesCategory Category="Standard" Type="File">
    <DynamicProperty>Author</DynamicProperty>
    <DynamicProperty>Manager</DynamicProperty>
    <DynamicProperty>Engr Approved By</DynamicProperty>
    <DynamicProperty>Engineer</DynamicProperty>
    <DynamicProperty>Designer</DynamicProperty>
    <DynamicProperty>Stock Number</DynamicProperty>
    <DynamicProperty>Part Number</DynamicProperty>
    <DynamicProperty>Mfg Approved By</DynamicProperty>
    <DynamicProperty>Material</DynamicProperty>
    <DynamicProperty>Cost</DynamicProperty>
    <DynamicProperty>Company</DynamicProperty>
    <DynamicProperty>Title</DynamicProperty>
    <DynamicProperty>Subject</DynamicProperty>
    <DynamicProperty>Keywords</DynamicProperty>
    <DynamicProperty>Comments</DynamicProperty>
    <DynamicProperty>Description</DynamicProperty>
    <DynamicProperty>Project</DynamicProperty>
  </DynamicPropertiesCategory>
  <DynamicPropertiesCategory Category="Organisation" Type="CustomObject">
    <DynamicProperty>Title</DynamicProperty>
    <DynamicProperty>Description</DynamicProperty>
    <DynamicProperty>Ident Number</DynamicProperty>
  </DynamicPropertiesCategory>
  <DynamicPropertiesCategory Category="Person" Type="CustomObject">
    <DynamicProperty>Description</DynamicProperty>
    <DynamicProperty>Email Recipient</DynamicProperty>
    <DynamicProperty>First Name</DynamicProperty>
    <DynamicProperty>Last Name</DynamicProperty>
    <DynamicProperty>Ident Number</DynamicProperty>
  </DynamicPropertiesCategory>
  <DynamicPropertiesCategory Category="Transmittal" Type="CustomObject">
    <DynamicProperty>Title</DynamicProperty>
    <DynamicProperty>Description</DynamicProperty>
    <DynamicProperty>Ident Number</DynamicProperty>
  </DynamicPropertiesCategory>
  <DynamicPropertiesCategory Category="Project" Type="Folder">
    <DynamicProperty>Title</DynamicProperty>
    <DynamicProperty>Description</DynamicProperty>
    <DynamicProperty>Date Start</DynamicProperty>
    <DynamicProperty>Date End</DynamicProperty>
    <DynamicProperty>Customer</DynamicProperty>
    <DynamicProperty>Ident Number</DynamicProperty>
    <DynamicProperty>Project Number01</DynamicProperty>
    <DynamicProperty>Project Number</DynamicProperty>
    <DynamicProperty>Project Title</DynamicProperty>
    <DynamicProperty>Project</DynamicProperty>
  </DynamicPropertiesCategory>
  <DynamicPropertiesCategory Category="Drawing AutoCAD" Type="FILE">
    <DynamicProperty>Title</DynamicProperty>
    <DynamicProperty>Description</DynamicProperty>
    <DynamicProperty>Material</DynamicProperty>
    <DynamicProperty>Part Number</DynamicProperty>
    <DynamicProperty>Project</DynamicProperty>
    <DynamicProperty>Format</DynamicProperty>
    <DynamicProperty>Dimensions/Size</DynamicProperty>
    <DynamicProperty>Source File</DynamicProperty>
    <DynamicProperty>Mass</DynamicProperty>
    <DynamicProperty>Scale</DynamicProperty>
    <DynamicProperty>Sheet</DynamicProperty>
    <DynamicProperty Hidden="True">DWG Type</DynamicProperty>
  </DynamicPropertiesCategory>
  <DynamicPropertiesCategory Category="Folder" Type="Folder">
    <DynamicProperty>Title</DynamicProperty>
    <DynamicProperty>Description</DynamicProperty>
    <DynamicProperty>FLCwsID</DynamicProperty>
    <DynamicProperty>FLCdmsID</DynamicProperty>
  </DynamicPropertiesCategory>
  <DynamicPropertiesCategory Category="Task" Type="CustomObject">
    <DynamicProperty>Title</DynamicProperty>
    <DynamicProperty>Description</DynamicProperty>
    <DynamicProperty>Ident Number</DynamicProperty>
    <DynamicProperty>Date Start</DynamicProperty>
    <DynamicProperty>Date End</DynamicProperty>
  </DynamicPropertiesCategory>
  <DynamicPropertiesCategory Category="Drawing Inventor" Type="FILE">
    <DynamicProperty>Title</DynamicProperty>
    <DynamicProperty>Description</DynamicProperty>
    <DynamicProperty>Part Number</DynamicProperty>
    <DynamicProperty>Format</DynamicProperty>
    <DynamicProperty Hidden="True">Application Version</DynamicProperty>
    <DynamicProperty>Scale</DynamicProperty>
    <DynamicProperty>Sheet</DynamicProperty>
    <DynamicProperty>Source File</DynamicProperty>
  </DynamicPropertiesCategory>
  <DynamicPropertiesCategory Category="Blechteil" Type="File">
    <DynamicProperty>Titel</DynamicProperty>
    <DynamicProperty>Material</DynamicProperty>
    <DynamicProperty>Teilenummer</DynamicProperty>
    <DynamicProperty>Abmessungen</DynamicProperty>
    <DynamicProperty>Halbzeug</DynamicProperty>
    <DynamicProperty>Gewicht</DynamicProperty>
    <DynamicProperty>Anwendungsversion</DynamicProperty>
    <DynamicProperty>Ersetzt durch</DynamicProperty>
    <DynamicProperty>Entstanden aus</DynamicProperty>
    <DynamicProperty>Titel EN</DynamicProperty>
    <DynamicProperty>Blechstärke</DynamicProperty>
    <DynamicProperty>Werksnorm</DynamicProperty>
    <DynamicProperty>Länge (Zuschnitt)</DynamicProperty>
    <DynamicProperty>EV-Kennung</DynamicProperty>
    <DynamicProperty>Halbzeugnummer</DynamicProperty>
    <DynamicProperty>Beschreibung</DynamicProperty>
  </DynamicPropertiesCategory>
  <DynamicPropertiesCategory Category="Bauteil" Type="File">
    <DynamicProperty>Titel</DynamicProperty>
    <DynamicProperty>Material</DynamicProperty>
    <DynamicProperty>Teilenummer</DynamicProperty>
    <DynamicProperty>Abmessungen</DynamicProperty>
    <DynamicProperty>Gewicht</DynamicProperty>
    <DynamicProperty>Anwendungsversion</DynamicProperty>
    <DynamicProperty>Beschreibung</DynamicProperty>
    <DynamicProperty>Halbzeugnummer</DynamicProperty>
    <DynamicProperty>EV-Kennung</DynamicProperty>
    <DynamicProperty>Halbzeug</DynamicProperty>
    <DynamicProperty>Werksnorm</DynamicProperty>
    <DynamicProperty>Ersetzt durch</DynamicProperty>
    <DynamicProperty>Entstanden aus</DynamicProperty>
    <DynamicProperty>Titel EN</DynamicProperty>
    <DynamicProperty>Länge (Zuschnitt)</DynamicProperty>
  </DynamicPropertiesCategory>
  <DynamicPropertiesCategory Category="Ordner" Type="Folder">
    <DynamicProperty>Titel</DynamicProperty>
    <DynamicProperty>Beschreibung</DynamicProperty>
    <DynamicProperty>Typbezeichnung</DynamicProperty>
  </DynamicPropertiesCategory>
  <DynamicPropertiesCategory Category="Klasse" Type="CustomObject">
    <DynamicProperty>Klasse</DynamicProperty>
    <DynamicProperty>Gruppe</DynamicProperty>
    <DynamicProperty>Untergruppe</DynamicProperty>
    <DynamicProperty>Segment</DynamicProperty>
    <DynamicProperty>Hauptgruppe</DynamicProperty>
  </DynamicPropertiesCategory>
  <DynamicPropertiesCategory Category="Kaufteil" Type="File">
    <DynamicProperty>Titel</DynamicProperty>
    <DynamicProperty>Beschreibung</DynamicProperty>
    <DynamicProperty>Material</DynamicProperty>
    <DynamicProperty>Teilenummer</DynamicProperty>
    <DynamicProperty>Abmessungen</DynamicProperty>
    <DynamicProperty>EV-Kennung</DynamicProperty>
    <DynamicProperty>Gewicht</DynamicProperty>
    <DynamicProperty>Titel EN</DynamicProperty>
    <DynamicProperty>Sub-Typ</DynamicProperty>
    <DynamicProperty>Anwendungsversion</DynamicProperty>
    <DynamicProperty>Ersetzt durch</DynamicProperty>
    <DynamicProperty>Entstanden aus</DynamicProperty>
    <DynamicProperty>Artikeltyp</DynamicProperty>
  </DynamicPropertiesCategory>
  <DynamicPropertiesCategory Category="3D Komponente" Type="File">
    <DynamicProperty>Beschreibung</DynamicProperty>
    <DynamicProperty>Werksnorm</DynamicProperty>
    <DynamicProperty>Sub-Typ</DynamicProperty>
    <DynamicProperty>Dicke/Durchm.</DynamicProperty>
    <DynamicProperty>Länge</DynamicProperty>
    <DynamicProperty>Breite</DynamicProperty>
    <DynamicProperty>Entstanden aus</DynamicProperty>
    <DynamicProperty>Titel EN</DynamicProperty>
    <DynamicProperty>Länge (Zuschnitt)</DynamicProperty>
    <DynamicProperty>Identnummer</DynamicProperty>
    <DynamicProperty>Titel</DynamicProperty>
    <DynamicProperty>Gewicht</DynamicProperty>
    <DynamicProperty>EV-Kennung</DynamicProperty>
    <DynamicProperty>Halbzeug</DynamicProperty>
    <DynamicProperty>Abmessungen</DynamicProperty>
    <DynamicProperty>Halbzeugnummer</DynamicProperty>
    <DynamicProperty>Teilenummer</DynamicProperty>
    <DynamicProperty>Material</DynamicProperty>
    <DynamicProperty>Ersetzt durch</DynamicProperty>
    <DynamicProperty>Anwendungsversion</DynamicProperty>
  </DynamicPropertiesCategory>
</DynamicProperties>